{"settings":{"textcolor":"#8c89ab","characterIDs":10,"dice":["1d4","1d20","1d100","1d2","1d1000","1d3","4d20"],"rooms":{},"room":"","buttons":true,"echeck":true,"notify":{"Cryoite-0":{"IC":true,"OOC":false}}},"characters":[[[{"id":"Hiroshima-0","name":"Empt","icon":590,"icpos":{"left":0,"top":0},"nameColor":"#a12b2b","color":"#828282","fontStyle":"Times","customHTML":"","textHTML":""},{"id":"Hiroshima-0","name":"Empt","icon":591,"icpos":{"left":0,"top":0},"nameColor":"#a12b2b","color":"#828282","fontStyle":"Times","customHTML":"","textHTML":""},{"id":"Hiroshima-0","name":"Empt","icon":592,"icpos":{"left":0,"top":0},"nameColor":"#a12b2b","color":"#828282","fontStyle":"Times","customHTML":"","textHTML":""},{"id":"Hiroshima-0","name":"Empt","icon":592,"icpos":{"left":50,"top":0},"nameColor":"#a12b2b","color":"#828282","fontStyle":"Times","customHTML":"","textHTML":""},{"id":"Hiroshima-0","name":"Empt","icon":592,"icpos":{"left":0,"top":50},"nameColor":"#a12b2b","color":"#828282","fontStyle":"Times","customHTML":"","textHTML":""},{"id":"Hiroshima-0","name":"Empt","icon":592,"icpos":{"left":50,"top":50},"nameColor":"#a12b2b","color":"#828282","fontStyle":"Times","customHTML":"","textHTML":""},{"id":"Hiroshima-0","name":"Empt","icon":593,"icpos":{"left":0,"top":0},"nameColor":"#a12b2b","color":"#828282","fontStyle":"Times","customHTML":"","textHTML":""},{"id":"Hiroshima-0","name":"Empt","icon":593,"icpos":{"left":50,"top":0},"nameColor":"#a12b2b","color":"#828282","fontStyle":"Times","customHTML":"","textHTML":""},{"id":"Hiroshima-0","name":"Empt","icon":593,"icpos":{"left":100,"top":0},"nameColor":"#a12b2b","color":"#828282","fontStyle":"Times","customHTML":"","textHTML":""},{"id":"Hiroshima-0","name":"Empt","icon":562,"icpos":{"left":0,"top":0},"nameColor":"#a12b2b","color":"#828282","fontStyle":"Times","customHTML":"","textHTML":""},{"id":"Hiroshima-0","name":"Empt","icon":579,"icpos":{"left":0,"top":50},"nameColor":"#a12b2b","color":"#828282","fontStyle":"Times","customHTML":"","textHTML":""},{"id":"Hiroshima-0","name":"Empt","icon":593,"icpos":{"left":50,"top":50},"nameColor":"#a12b2b","color":"#828282","fontStyle":"Times","customHTML":"","textHTML":""}],[{"id":"Hiroshima-5","name":"Zerok","icon":662,"icpos":{"left":0,"top":0},"nameColor":"#dbbcbc","color":"#dec7c7","fontStyle":"Times New Roman","customHTML":"","textHTML":""},{"id":"Hiroshima-5","name":"Zerok","icon":539,"icpos":{"left":50,"top":0},"nameColor":"#dbbcbc","color":"#dec7c7","fontStyle":"Times New Roman","customHTML":"","textHTML":""},{"id":"Hiroshima-5","name":"Zerok","icon":481,"icpos":{"left":0,"top":0},"nameColor":"#dbbcbc","color":"#dec7c7","fontStyle":"Times New Roman","customHTML":"","textHTML":""},{"id":"Hiroshima-5","name":"Zerok","icon":481,"icpos":{"left":50,"top":0},"nameColor":"#dbbcbc","color":"#dec7c7","fontStyle":"Times New Roman","customHTML":"","textHTML":""},{"id":"Hiroshima-5","name":"Zerok","icon":481,"icpos":{"left":100,"top":0},"nameColor":"#dbbcbc","color":"#dec7c7","fontStyle":"Times New Roman","customHTML":"","textHTML":""},{"id":"Hiroshima-5","name":"Zerok","icon":481,"icpos":{"left":0,"top":50},"nameColor":"#dbbcbc","color":"#dec7c7","fontStyle":"Times New Roman","customHTML":"","textHTML":""},{"id":"Hiroshima-5","name":"Zerok","icon":481,"icpos":{"left":50,"top":50},"nameColor":"#dbbcbc","color":"#dec7c7","fontStyle":"Times New Roman","customHTML":"","textHTML":""},{"id":"Hiroshima-5","name":"Zerok","icon":481,"icpos":{"left":100,"top":50},"nameColor":"#dbbcbc","color":"#dec7c7","fontStyle":"Times New Roman","customHTML":"","textHTML":""},{"id":"Hiroshima-5","name":"Zerok","icon":481,"icpos":{"left":0,"top":100},"nameColor":"#dbbcbc","color":"#dec7c7","fontStyle":"Times New Roman","customHTML":"","textHTML":""},{"id":"Hiroshima-5","name":"Zerok","icon":539,"icpos":{"left":0,"top":0},"nameColor":"#dbbcbc","color":"#dec7c7","fontStyle":"Times New Roman","customHTML":"","textHTML":""},{"id":"Hiroshima-5","name":"Zerok","icon":481,"icpos":{"left":50,"top":100},"nameColor":"#dbbcbc","color":"#dec7c7","fontStyle":"Times New Roman","customHTML":"","textHTML":""}],[{"id":"Hiroshima-1","name":"Mizore","icon":302,"icpos":{"left":0,"top":0},"nameColor":"#a1a1a1","color":"#a3a3a3","fontStyle":"TW Cen MT","customHTML":"","textHTML":""},{"id":"Hiroshima-1","name":"Mizore","icon":305,"icpos":{"left":0,"top":0},"nameColor":"#a1a1a1","color":"#a3a3a3","fontStyle":"TW Cen MT","customHTML":"","textHTML":""},{"id":"Hiroshima-1","name":"Mizore","icon":305,"icpos":{"left":50,"top":0},"nameColor":"#a1a1a1","color":"#a3a3a3","fontStyle":"TW Cen MT","customHTML":"","textHTML":""},{"id":"Hiroshima-1","name":"Mizore","icon":305,"icpos":{"left":100,"top":0},"nameColor":"#a1a1a1","color":"#a3a3a3","fontStyle":"TW Cen MT","customHTML":"","textHTML":""},{"id":"Hiroshima-1","name":"Mizore","icon":305,"icpos":{"left":150,"top":0},"nameColor":"#a1a1a1","color":"#a3a3a3","fontStyle":"TW Cen MT","customHTML":"","textHTML":""},{"id":"Hiroshima-1","name":"Mizore","icon":305,"icpos":{"left":0,"top":50},"nameColor":"#a1a1a1","color":"#a3a3a3","fontStyle":"TW Cen MT","customHTML":"","textHTML":""},{"id":"Hiroshima-1","name":"Mizore","icon":305,"icpos":{"left":50,"top":50},"nameColor":"#a1a1a1","color":"#a3a3a3","fontStyle":"TW Cen MT","customHTML":"","textHTML":""},{"id":"Hiroshima-1","name":"Mizore","icon":305,"icpos":{"left":100,"top":50},"nameColor":"#a1a1a1","color":"#a3a3a3","fontStyle":"TW Cen MT","customHTML":"","textHTML":""},{"id":"Hiroshima-1","name":"Mizore","icon":305,"icpos":{"left":150,"top":50},"nameColor":"#a1a1a1","color":"#a3a3a3","fontStyle":"TW Cen MT","customHTML":"","textHTML":""},{"id":"Hiroshima-1","name":"Mizore","icon":305,"icpos":{"left":0,"top":100},"nameColor":"#a1a1a1","color":"#a3a3a3","fontStyle":"TW Cen MT","customHTML":"","textHTML":""},{"id":"Hiroshima-1","name":"Mizore","icon":305,"icpos":{"left":50,"top":100},"nameColor":"#a1a1a1","color":"#a3a3a3","fontStyle":"TW Cen MT","customHTML":"","textHTML":""},{"id":"Hiroshima-1","name":"Mizore","icon":305,"icpos":{"left":100,"top":100},"nameColor":"#a1a1a1","color":"#a3a3a3","fontStyle":"TW Cen MT","customHTML":"","textHTML":""},{"id":"Hiroshima-1","name":"Mizore","icon":305,"icpos":{"left":150,"top":100},"nameColor":"#a1a1a1","color":"#a3a3a3","fontStyle":"TW Cen MT","customHTML":"","textHTML":""},{"id":"Hiroshima-1","name":"Mizore","icon":305,"icpos":{"left":0,"top":150},"nameColor":"#a1a1a1","color":"#a3a3a3","fontStyle":"TW Cen MT","customHTML":"","textHTML":""},{"id":"Hiroshima-1","name":"Mizore","icon":306,"icpos":{"left":50,"top":0},"nameColor":"#a1a1a1","color":"#a3a3a3","fontStyle":"TW Cen MT","customHTML":"","textHTML":""},{"id":"Hiroshima-1","name":"Mizore","icon":306,"icpos":{"left":0,"top":0},"nameColor":"#a1a1a1","color":"#a3a3a3","fontStyle":"TW Cen MT","customHTML":"","textHTML":""},{"id":"Hiroshima-1","name":"Mizore","icon":336,"icpos":{"left":0,"top":0},"nameColor":"#a1a1a1","color":"#a3a3a3","fontStyle":"TW Cen MT","customHTML":"","textHTML":""}],[{"id":"Hiroshima-6","name":"Knat","icon":521,"icpos":{"left":0,"top":0},"nameColor":"#bf4a4a","color":"#e6e6e6","fontStyle":"Calibri","customHTML":"","textHTML":""}],[{"id":"Hiroshima-2","name":"Cristan","icon":299,"icpos":{"left":0,"top":0},"nameColor":"#009999","color":"#009494","fontStyle":"Times New Roman","customHTML":"","textHTML":""}],[{"id":"Hiroshima-7","name":"???","icon":622,"icpos":{"left":0,"top":0},"nameColor":"#8c5f8c","color":"#7d5f7d","fontStyle":"Times New Roman","customHTML":"","textHTML":""}],[{"id":"Hiroshima-8","name":"The Hooded Figure","icon":621,"icpos":{"left":0,"top":0},"nameColor":"#a82e2e","color":"#bf0000","fontStyle":"Times New Roman","customHTML":"","textHTML":""}],[{"id":"Hiroshima-9","name":"Zi'nek","icon":678,"icpos":{"left":0,"top":0},"nameColor":"#8c8c0b","color":"#9c3e00","fontStyle":"Garamond","customHTML":"","textHTML":""},{"id":"Hiroshima-9","name":"Zi'nek","icon":679,"icpos":{"left":0,"top":0},"nameColor":"#8c8c0b","color":"#9c3e00","fontStyle":"Garamond","customHTML":"","textHTML":""},{"id":"Hiroshima-9","name":"Zi'nek","icon":681,"icpos":{"left":0,"top":0},"nameColor":"#8c8c0b","color":"#9c3e00","fontStyle":"Garamond","customHTML":"","textHTML":""},{"id":"Hiroshima-9","name":"Zi'nek","icon":681,"icpos":{"left":50,"top":0},"nameColor":"#8c8c0b","color":"#9c3e00","fontStyle":"Garamond","customHTML":"","textHTML":""},{"id":"Hiroshima-9","name":"Zi'nek","icon":681,"icpos":{"left":100,"top":0},"nameColor":"#8c8c0b","color":"#9c3e00","fontStyle":"Garamond","customHTML":"","textHTML":""},{"id":"Hiroshima-9","name":"Zi'nek","icon":681,"icpos":{"left":0,"top":50},"nameColor":"#8c8c0b","color":"#9c3e00","fontStyle":"Garamond","customHTML":"","textHTML":""},{"id":"Hiroshima-9","name":"Zi'nek","icon":681,"icpos":{"left":50,"top":50},"nameColor":"#8c8c0b","color":"#9c3e00","fontStyle":"Garamond","customHTML":"","textHTML":""},{"id":"Hiroshima-9","name":"Zi'nek","icon":681,"icpos":{"left":100,"top":50},"nameColor":"#8c8c0b","color":"#9c3e00","fontStyle":"Garamond","customHTML":"","textHTML":""}]]]}